paloalto_panorama_sdk/__init__.py
paloalto_panorama_sdk/address_groups_manager.py
paloalto_panorama_sdk/address_manager.py
paloalto_panorama_sdk/device_groups_manager.py
paloalto_panorama_sdk/key_manager.py
paloalto_panorama_sdk/panorama_sdk.py
paloalto_panorama_sdk/post_rules_manager.py
paloalto_panorama_sdk/security_post_rules_manager.py
paloalto_panorama_sdk/service_groups_manager.py
paloalto_panorama_sdk/service_manager.py
paloalto_panorama_sdk/panorama_data_kit/__init__.py
paloalto_panorama_sdk/panorama_data_kit/address_data.py
paloalto_panorama_sdk/panorama_data_kit/address_group_data.py
paloalto_panorama_sdk/panorama_data_kit/adress_data.py
paloalto_panorama_sdk/panorama_data_kit/adress_group_data.py
paloalto_panorama_sdk/panorama_data_kit/device_group_data.py
paloalto_panorama_sdk/panorama_data_kit/security_post_rule_data.py
paloalto_panorama_sdk/panorama_data_kit/service_data.py
paloalto_panorama_sdk/panorama_data_kit/service_group_data.py
tests/__init__.py
tests/test_service.py
tests/PanoramaAPIMock/__init__.py
tests/PanoramaAPIMock/panoramaAPIMock.py
paloalto_panorama_sdk-0.0.10.dist-info/LICENSE
paloalto_panorama_sdk-0.0.10.dist-info/METADATA
paloalto_panorama_sdk-0.0.10.dist-info/WHEEL
paloalto_panorama_sdk-0.0.10.dist-info/top_level.txt
paloalto_panorama_sdk-0.0.10.dist-info/RECORD
