Metadata-Version: 2.1
Name: paloalto-panorama-sdk
Version: 0.0.10
Summary: This SDK is designed to make it easier to work with the Palo Alto Panorama API.
Author: Timo Riedinger
Author-email: timo.riedinger@bechtle.com
License: MIT
Classifier: Programming Language :: Python :: 3.11
License-File: LICENSE
Requires-Dist: backports.tarfile ==1.1.1
Requires-Dist: blinker ==1.8.1
Requires-Dist: certifi ==2024.2.2
Requires-Dist: charset-normalizer ==3.3.2
Requires-Dist: click ==8.1.7
Requires-Dist: dicttoxml ==1.7.16
Requires-Dist: docutils ==0.21.2
Requires-Dist: Flask ==3.0.3
Requires-Dist: idna ==3.7
Requires-Dist: importlib-metadata ==7.1.0
Requires-Dist: itsdangerous ==2.2.0
Requires-Dist: jaraco.classes ==3.4.0
Requires-Dist: jaraco.context ==5.3.0
Requires-Dist: jaraco.functools ==4.0.1
Requires-Dist: Jinja2 ==3.1.3
Requires-Dist: keyring ==25.2.0
Requires-Dist: markdown-it-py ==3.0.0
Requires-Dist: MarkupSafe ==2.1.5
Requires-Dist: mdurl ==0.1.2
Requires-Dist: more-itertools ==10.2.0
Requires-Dist: nh3 ==0.2.17
Requires-Dist: pkginfo ==1.10.0
Requires-Dist: Pygments ==2.17.2
Requires-Dist: python-dotenv ==1.0.1
Requires-Dist: readme-renderer ==43.0
Requires-Dist: requests ==2.31.0
Requires-Dist: requests-toolbelt ==1.0.0
Requires-Dist: rfc3986 ==2.0.0
Requires-Dist: rich ==13.7.1
Requires-Dist: twine ==5.0.0
Requires-Dist: urllib3 ==2.2.1
Requires-Dist: Werkzeug ==3.0.2
Requires-Dist: zipp ==3.18.1
